{
  "PartitionKey": "TrainUnitParameters",
  "Class": "SOB",
  "BaseClassType": "TankerGeneral",
  "CurveRes": 0.0,
  "Mass": 0.0,
  "Length": 1584.0,
  "DragA": 392455.0,
  "DragAmass": 713619.0,
  "DragB": 0.0,
  "DragBmass": 0.0,
  "DragC": 0.0,
  "DeltaDragC": 0.0,
  "MaxSpeed": 277778.0,
  "RotatingMassCoefficient": 0.0,
  "NumberOfCars": 1,
  "MechanicalBraking": 0.0,
  "Type": 0,
  "Propulsion": 6,
  "ProtectionSystem": null,
  "PreferedBraking": [
    [
      0.0,
      15.0
    ]
  ],
  "BrakedWeightPercentageG": 0,
  "BrakedWeightPercentageP": 0,
  "DisplayName": "SOB",
  "NumAxles": 4,
  "SupportedTypes": [],
  "MinimumCoastingSpeed": 0.0,
  "MinimumCoastingDistance": 0,
  "IsLoco": false,
  "SpeedometerDeviation": 0.0,
  "TractionPowerMap": null,
  "BrakingPowerMap": null,
  "BrakingCurves": [],
  "TractionCurves": [],
  "BrakingForce": 0.0,
  "BrakingPower": 0.0,
  "TractionForce": 0,
  "TractionPower": 0,
  "TractionEfficiency": 0.0,
  "BrakingEfficiency": 0.0
}